django_aioredis/__init__.py
django_aioredis/cache.py
django_aioredis-0.0.1.dist-info/METADATA
django_aioredis-0.0.1.dist-info/WHEEL
django_aioredis-0.0.1.dist-info/licenses/LICENSE
django_aioredis-0.0.1.dist-info/RECORD
