Metadata-Version: 2.4
Name: django-aioredis
Version: 0.0.1
Summary: This package provides a custom cache backend for Django that integrates with the asynchronous capabilities of the aioredis library.
Project-URL: Homepage, https://github.com/Alireza-Tabatabaeian/django-aioredis
Project-URL: Issues, https://github.com/Alireza-Tabatabaeian/django-aioredis/issues
Author-email: Alireza Tabatabaeian <alireza.tabatabaeian@gmail.com>
License: MIT License
License-File: LICENSE
Keywords: aioredis,async,cache,django,redis
Classifier: Development Status :: 3 - Alpha
Classifier: Environment :: Web Environment
Classifier: Framework :: Django
Classifier: Intended Audience :: Developers
Classifier: License :: OSI Approved :: MIT License
Classifier: Operating System :: OS Independent
Classifier: Programming Language :: Python :: 3
Requires-Python: >=3.8
Requires-Dist: aioredis
Requires-Dist: django
